pubsub/__init__.py
pubsub/pub.py
pubsub/sub.py
pubsubpy-2.3.0.dist-info/METADATA
pubsubpy-2.3.0.dist-info/RECORD
pubsubpy-2.3.0.dist-info/WHEEL
pubsubpy-2.3.0.dist-info/top_level.txt
tests/__init__.py
tests/kombu_mock.py
tests/pubsub.py
