Metadata-Version: 2.1
Name: pubsubpy
Version: 2.3.0
Summary: Client library for an AMQP-based pubsub.
Home-page: https://github.com/makingspace/pubsubpy
Author: John Sloboda
Author-email: sloboda@makespace.com
License: MIT
Platform: UNKNOWN
Classifier: Programming Language :: Python
Classifier: Programming Language :: Python :: 2
Classifier: Programming Language :: Python :: 2.7
Classifier: Programming Language :: Python :: 3
Classifier: Programming Language :: Python :: 3.4
Classifier: Programming Language :: Python :: 3.6
Requires-Dist: future
Requires-Dist: kombu
